cloudpy_org/__init__.py
cloudpy_org/aws.py
cloudpy_org/aws_with_changes.py
cloudpy_org/client_usage.py
cloudpy_org/docs.py
cloudpy_org/imgedit.py
cloudpy_org/infoflow_chat.py
cloudpy_org/oft.py
cloudpy_org/tools.py
cloudpy_org/web.py
cloudpy_org/web_client_usage.py
cloudpy_org-1.6.5.dist-info/METADATA
cloudpy_org-1.6.5.dist-info/WHEEL
cloudpy_org-1.6.5.dist-info/top_level.txt
cloudpy_org-1.6.5.dist-info/RECORD
