Metadata-Version: 2.1
Name: cloudpy-org
Version: 1.6.5
Summary: Cloud data pipeline organization and automation library. Includes AWS framework manager API.
Home-page: https://www.cloudpy.org/
Author: cloudpy.org
Author-email: admin@cloudpy.org
License: MIT
Platform: UNKNOWN
Classifier: Intended Audience :: Developers
Classifier: License :: OSI Approved :: MIT License
Classifier: Programming Language :: Python
Classifier: Programming Language :: Python :: 3
Classifier: Programming Language :: Python :: 3.6
Classifier: Programming Language :: Python :: 3.7
Classifier: Programming Language :: Python :: 3.8
Classifier: Programming Language :: Python :: 3.9
Classifier: Operating System :: OS Independent
Requires-Dist: pandas
Requires-Dist: pandasql
Requires-Dist: requests
Requires-Dist: boto3
Requires-Dist: awswrangler
Requires-Dist: tqdm
Requires-Dist: botocore
Requires-Dist: numpy
Requires-Dist: cryptography
Requires-Dist: s3fs
Requires-Dist: pillow
Requires-Dist: flask
Requires-Dist: APScheduler
Requires-Dist: pytz
Requires-Dist: soundfile
Requires-Dist: SpeechRecognition
Requires-Dist: openai
Requires-Dist: pyttsx3
Requires-Dist: sounddevice
Requires-Dist: scipy
Requires-Dist: werkzeug
Requires-Dist: PyPDF2
